[{
    "id":1,
    "title":"洗发洗护",
    "list":[{
        "id":101,
        "name":"其他头发问题"
    },
    {
        "id":102,
        "name":"头发造型"
    },
    {
        "id":103,
        "name":"美发护发工具"
    },
    {
        "id":104,
        "name":"洗发皂"
    },
    {
        "id":105,
        "name":"梳子"
    },
    {
        "id":106,
        "name":"护发精油"
    },
    {
        "id":107,
        "name":"护发素"
    },
    {
        "id":108,
        "name":"洗发水"
    },
    {
        "id":109,
        "name":"发膜"
    },
    {
        "id":110,
        "name":"洗护发套装"
    },
    {
        "id":111,
        "name":"染发膏"
    }
]
},
{
    "id":2,
    "title":"身体护理",
    "list":[{
        "id":201,
        "name":"沐浴清洁"
    },
    {
        "id":202,
        "name":"身体护理"
    },
    {
        "id":203,
        "name":"足部护理"
    },
    {
        "id":204,
        "name":"手部护理"
    }
]
},
{
    "id":3,
    "title":"口腔护理",
    "list":[{
        "id":301,
        "name":"其他口腔护理"
    },
    {
        "id":302,
        "name":"牙线"
    },
    {
        "id":303,
        "name":"牙粉"
    },
    {
        "id":304,
        "name":"牙刷"
    },
    {
        "id":305,
        "name":"牙膏"
    },
    {
        "id":306,
        "name":"漱口水"
    },
    {
        "id":307,
        "name":"口腔护理套装"
    }
]
    
},
{
    "id":4,
    "title":"女性护理",
    "list":[{
        "id":201,
        "name":"其他女性护理"
    },
    {
        "id":202,
        "name":"私密洗液"
    },
    {
        "id":203,
        "name":"卫生棉条"
    },
    {
        "id":201,
        "name":"其他女性护理"
    },
    {
        "id":202,
        "name":"私密洗液"
    },
    {
        "id":203,
        "name":"卫生棉条"
    }
    
]
},
{
    "id":5,
    "title":"成人健康",
    "list":[{
        "id":201,
        "name":"口罩"
    },
    {
        "id":202,
        "name":"暖贴"
    },
    {
        "id":203,
        "name":"眼罩"
    } ,
    {
        "id":201,
        "name":"口罩"
    },
    {
        "id":202,
        "name":"暖贴"
    },
    {
        "id":203,
        "name":"眼罩"
    } 
]
},
{
    "id":6,
    "title":"宠物生活",
    "list":[{
        "id":201,
        "name":"宠物日常用品"
    }
]
}
]